itt/__init__.py
itt/_metadata.py
itt/utilities/__init__.py
itt/utilities/mac_elevate.py
itt/utilities/monkey_patch.py
itt/utilities/remove_old_config_db.py
itt-2.83.5.dist-info/LICENSE.txt
itt-2.83.5.dist-info/METADATA
itt-2.83.5.dist-info/WHEEL
itt-2.83.5.dist-info/entry_points.txt
itt-2.83.5.dist-info/top_level.txt
itt-2.83.5.dist-info/RECORD
