Metadata-Version: 2.1
Name: itt
Version: 2.83.5
Summary: Provides a set of useful test tools written in Python.
Home-page: https://bitbucket.org/davisowb/integration-test-tools.git
Author: Oli Davis & Hywel Thomas
Author-email: oli.davis@me.com, hywel.thomas@mac.com
License: MIT
Download-URL: https://bitbucket.org/davisowb/integration-test-tools.git/get/2.83.5.tar
Platform: UNKNOWN
Classifier: Development Status :: 3 - Alpha
Classifier: Intended Audience :: Developers
Classifier: License :: OSI Approved :: MIT License
Classifier: Programming Language :: Python :: 2
Classifier: Programming Language :: Python :: 2.7
Classifier: Programming Language :: Python :: 3
Classifier: Programming Language :: Python :: 3.6
Classifier: Topic :: Utilities
License-File: LICENSE.txt
Requires-Dist: future (>=0.16.0)
Requires-Dist: better-exceptions (>=0.1.6)
Requires-Dist: requests[security] (>=2.18.4)
Requires-Dist: appdirs (>=1.4.0)
Requires-Dist: attrs (>=17.4.0)
Requires-Dist: apiutil (==1.9.6)
Requires-Dist: cachingutil (==1.2.7)
Requires-Dist: classutils (==1.18.1)
Requires-Dist: cli-utils (==1.0.6)
Requires-Dist: configurationutil[ui] (==3.7.6)
Requires-Dist: conversionutil (==1.4.6)
Requires-Dist: dbhelperutil (==1.1.0)
Requires-Dist: fdutil (==1.16.1)
Requires-Dist: logging-helper (==1.9.0)
Requires-Dist: misguided-xml (==1.1.0)
Requires-Dist: networkutil (==1.19.12)
Requires-Dist: pydnserver (==2.4.2)
Requires-Dist: pyhttpintercept (==0.34.1)
Requires-Dist: reportutil (==0.0.6)
Requires-Dist: simpil (==1.2.0)
Requires-Dist: stateutil (==1.4.0)
Requires-Dist: tableutil (==2.4.5)
Requires-Dist: timingsutil (==1.7.0)
Requires-Dist: uiutil (==1.38.0)
Requires-Dist: voicerss-tts (==1.0.6)
Requires-Dist: pyserial (>=3.4)
Requires-Dist: psutil (>=4.3.1)
Requires-Dist: openpyxl (>=2.4.0)
Requires-Dist: pycountry (==18.5.26)
Requires-Dist: wheel (>=0.32.3)
Provides-Extra: test
